AUTHORS.rst
CONTRIBUTING.rst
HISTORY.rst
LICENSE.rst
MANIFEST.in
README.rst
requirements-dev.txt
requirements.txt
setup.cfg
setup.py
docs/Makefile
docs/authors.rst
docs/conf.py
docs/contributing.rst
docs/history.rst
docs/index.rst
docs/overview.rst
docs/api/drf_braces.fields.custom.rst
docs/api/drf_braces.fields.mixins.rst
docs/api/drf_braces.fields.modified.rst
docs/api/drf_braces.fields.rst
docs/api/drf_braces.forms.fields.rst
docs/api/drf_braces.forms.rst
docs/api/drf_braces.forms.serializer_form.rst
docs/api/drf_braces.mixins.rst
docs/api/drf_braces.parsers.rst
docs/api/drf_braces.rst
docs/api/drf_braces.serializers.enforce_validation_serializer.rst
docs/api/drf_braces.serializers.form_serializer.rst
docs/api/drf_braces.serializers.rst
docs/api/drf_braces.tests.fields.rst
docs/api/drf_braces.tests.fields.test_custom.rst
docs/api/drf_braces.tests.fields.test_fields.rst
docs/api/drf_braces.tests.fields.test_mixins.rst
docs/api/drf_braces.tests.fields.test_modified.rst
docs/api/drf_braces.tests.forms.rst
docs/api/drf_braces.tests.forms.test_fields.rst
docs/api/drf_braces.tests.forms.test_serializer_form.rst
docs/api/drf_braces.tests.rst
docs/api/drf_braces.tests.serializers.rst
docs/api/drf_braces.tests.serializers.test_enforce_validation_serializer.rst
docs/api/drf_braces.tests.serializers.test_form_serialzier.rst
docs/api/drf_braces.tests.test_mixins.rst
docs/api/drf_braces.tests.test_parsers.rst
docs/api/drf_braces.utils.rst
docs/api/modules.rst
drf_braces/__init__.py
drf_braces/mixins.py
drf_braces/models.py
drf_braces/parsers.py
drf_braces/renderers.py
drf_braces/utils.py
drf_braces/fields/__init__.py
drf_braces/fields/_fields.py
drf_braces/fields/custom.py
drf_braces/fields/mixins.py
drf_braces/fields/modified.py
drf_braces/forms/__init__.py
drf_braces/forms/fields.py
drf_braces/forms/serializer_form.py
drf_braces/serializers/__init__.py
drf_braces/serializers/enforce_validation_serializer.py
drf_braces/serializers/form_serializer.py
totallylegit_django_rest_framework_braces.egg-info/PKG-INFO
totallylegit_django_rest_framework_braces.egg-info/SOURCES.txt
totallylegit_django_rest_framework_braces.egg-info/dependency_links.txt
totallylegit_django_rest_framework_braces.egg-info/requires.txt
totallylegit_django_rest_framework_braces.egg-info/top_level.txt