Metadata-Version: 2.1
Name: totallylegit-django-rest-framework-braces
Version: 0.4.3
Summary: Collection of utilities for working with DRF
Home-page: https://github.com/dealertrack/django-rest-framework-braces
Author: Original: Miroslav Shubernetskiy, Current: Holden Karau
License: MIT
Keywords: django-rest-framework
Classifier: Intended Audience :: Developers
Classifier: Natural Language :: English
Classifier: License :: OSI Approved :: MIT License
Classifier: Programming Language :: Python
Classifier: Programming Language :: Python :: 3.10
Classifier: Programming Language :: Python :: 3.11
Classifier: Development Status :: 2 - Pre-Alpha
License-File: LICENSE.rst
License-File: AUTHORS.rst
Requires-Dist: dateutils
Requires-Dist: django
Requires-Dist: djangorestframework
Requires-Dist: pytz
Requires-Dist: six
Requires-Dist: setuptools
